actico_ml/__init__.py
actico_ml/export_util.py
actico_ml-0.0.7.dist-info/LICENSE.txt
actico_ml-0.0.7.dist-info/METADATA
actico_ml-0.0.7.dist-info/WHEEL
actico_ml-0.0.7.dist-info/top_level.txt
actico_ml-0.0.7.dist-info/RECORD
