Metadata-Version: 2.1
Name: actico-ml
Version: 0.0.7
Summary: Functions to upload and export trained ml models
Home-page: https://www.actico.com/
Author: ACTICO GmbH
License: MIT License
Platform: OS Independent
Classifier: Programming Language :: Python :: 3
Classifier: License :: OSI Approved :: MIT License
Classifier: Operating System :: OS Independent
Requires-Python: >=3.7
License-File: LICENSE.txt
Requires-Dist: requests
Requires-Dist: h2o (>=3.36.0.1)
Provides-Extra: spark
Requires-Dist: pyspark (==3.1.2) ; extra == 'spark'
